revbranch.py
revbranch-0.5.dist-info/LICENSE
revbranch-0.5.dist-info/METADATA
revbranch-0.5.dist-info/WHEEL
revbranch-0.5.dist-info/entry_points.txt
revbranch-0.5.dist-info/top_level.txt
revbranch-0.5.dist-info/RECORD
